idika-0.3.1.dist-info/METADATA
idika-0.3.1.dist-info/WHEEL
idika-0.3.1.dist-info/license_files/LICENSE
idika.libs/libgcc_s-1e52349c.so.1
idika/__init__.py
idika/idika.abi3.so
idika-0.3.1.dist-info/RECORD
