Metadata-Version: 2.3
Name: idika
Version: 0.3.1
Classifier: Programming Language :: Python :: 3
Classifier: License :: OSI Approved :: MIT License
Classifier: Operating System :: OS Independent
License-File: LICENSE
Summary: Unique ids generator implemented in rust
Author: jackkweyunga <jackkweyunga@gmail.com>
Author-email: Jack Kweyunga <jackkweyunga@gmail.com>
Requires-Python: >3.8
Project-URL: Homepage, https://github.com/jackkweyunga/idika
Project-URL: Bug Tracker, https://github.com/jackkweyunga/idika/issues
